nonebot_plugin_setu_now/__init__.py
nonebot_plugin_setu_now/config.py
nonebot_plugin_setu_now/data_source.py
nonebot_plugin_setu_now/database.py
nonebot_plugin_setu_now/img_utils.py
nonebot_plugin_setu_now/models.py
nonebot_plugin_setu_now/perf_timer.py
nonebot_plugin_setu_now/r18_whitelist.py
nonebot_plugin_setu_now/utils.py
nonebot_plugin_setu_now/aioutils/__init__.py
nonebot_plugin_setu_now/aioutils/_main.py
nonebot_plugin_setu_now-0.6.6.dist-info/METADATA
nonebot_plugin_setu_now-0.6.6.dist-info/WHEEL
nonebot_plugin_setu_now-0.6.6.dist-info/licenses/LICENSE
nonebot_plugin_setu_now-0.6.6.dist-info/RECORD
