Metadata-Version: 2.3
Name: nonebot-plugin-setu-now
Version: 0.6.6
Summary: 另一个色图插件
Project-URL: homepage, https://github.com/kexue-z/nonebot-plugin-setu-now
Author-email: kexue <xana278@foxmail.com>
License: MIT License
Keywords: nonebot2
Requires-Python: <4.0,>=3.11
Requires-Dist: httpx>=0.28.0
Requires-Dist: nonebot-adapter-onebot>=2.4.6
Requires-Dist: nonebot-plugin-localstore>=0.7.2
Requires-Dist: nonebot-plugin-tortoise-orm>=0.1.4
Requires-Dist: nonebot2>=2.4.0
Requires-Dist: pillow>=11.0.0
Requires-Dist: pydantic>=2.10.3
